<?xml version="1.0" encoding="UTF-8" standalone="no" ?>
<Application>

  <Header>
    <Version val="13030.00"/>
    <WithIsn val="Y"/>
    <_InternalTask val="N"/>
    <IsRoot val="N"/>
    <InIndex val="N"/>
    <UniqueISNConvState val="12"/>
  </Header>

  <ProgramsRepository>
    <Programs>
      <Task MainProgram="N">
        <Header Description="  S.顧客コード判定(both)" ISN_2="1" LastIsn="3" id="372">
          <ExecutionRight comp="-1"/>
          <Resident val="N"/>
          <SQL val="N"/>
          <ReturnValue>
            <ReturnValueAttr/>
            <TSK_PARAMS val="6"/>
            <ParametersAttributes>
              <Attr MgAttr="A"/>
              <Attr MgAttr="N"/>
              <Attr MgAttr="B"/>
              <Attr MgAttr="B"/>
              <Attr MgAttr="A"/>
              <Attr MgAttr="B"/>
            </ParametersAttributes>
          </ReturnValue>
          <SqlWhereExist val="N"/>
          <TaskType val="B"/>
          <External val="N"/>
          <Offline val="N"/>
          <FormType val="N"/>
          <DotNetObjectExists val="N"/>
          <LastModified _date="737719" _time="55932" date="2020/10/21" time="15:32:12"/>
        </Header>
        <ItemIsn val="15"/>
        <Resource>
          <Columns>
            <Column id="1" name="Pv.入力顧客コード">
              <PropertyList model="FIELD">
                <Model attr_obj="FIELD_ALPHA" comp="-1" id="1" obj="9"/>
                <StoredAs id="173" val="1"/>
                <Definition id="175" val="2"/>
              </PropertyList>
            </Column>
            <Column id="2" name="Pv.顧客コード">
              <PropertyList model="FIELD">
                <Model attr_obj="FIELD_NUMERIC" comp="-1" id="1" obj="5"/>
                <StoredAs id="173" val="1"/>
                <Definition id="175" val="2"/>
              </PropertyList>
            </Column>
            <Column id="3" name="PFC.SvrData">
              <PropertyList model="FIELD">
                <Model attr_obj="FIELD_LOGICAL" id="1"/>
                <StoredAs id="173"/>
                <_FieldStyle id="276" val="1"/>
              </PropertyList>
            </Column>
            <Column id="4" name="PF.スキャンコードエラー">
              <PropertyList model="FIELD">
                <Model attr_obj="FIELD_LOGICAL" id="1"/>
                <GuiDisplay id="158">
                  <PropertyList model="CTRL_GUI0_EDIT">
                    <Font id="50" val="101"/>
                    <Color id="51" val="101"/>
                    <V11Style id="539" val="4"/>
                  </PropertyList>
                </GuiDisplay>
                <GuiDisplayTable id="159">
                  <PropertyList model="CTRL_GUI0_EDIT">
                    <Font id="50" val="101"/>
                    <Color id="51" val="101"/>
                  </PropertyList>
                </GuiDisplayTable>
                <GuiOutput id="160">
                  <PropertyList model="CTRL_GUI1_EDIT">
                    <Font id="50" val="101"/>
                    <Color id="51" val="101"/>
                  </PropertyList>
                </GuiOutput>
                <GuiOutputTable id="161">
                  <PropertyList model="CTRL_GUI1_EDIT">
                    <Font id="50" val="101"/>
                    <Color id="51" val="101"/>
                  </PropertyList>
                </GuiOutputTable>
                <NullValue id="167"/>
                <StoredAs id="173" val="1"/>
                <Definition id="175" val="2"/>
              </PropertyList>
            </Column>
            <Column id="5" name="PS.スキャンバーコード(設定値)">
              <PropertyList model="FIELD">
                <Model attr_obj="FIELD_ALPHA" comp="-1" id="1" obj="9"/>
                <StoredAs id="173" val="1"/>
                <Definition id="175" val="2"/>
              </PropertyList>
            </Column>
            <Column id="6" name="PF.エージェントエラー">
              <PropertyList model="FIELD">
                <Model attr_obj="FIELD_LOGICAL" id="1"/>
                <GuiDisplay id="158">
                  <PropertyList model="CTRL_GUI0_EDIT">
                    <Font id="50" val="101"/>
                    <Color id="51" val="101"/>
                    <V11Style id="539" val="4"/>
                  </PropertyList>
                </GuiDisplay>
                <GuiDisplayTable id="159">
                  <PropertyList model="CTRL_GUI0_EDIT">
                    <Font id="50" val="101"/>
                    <Color id="51" val="101"/>
                  </PropertyList>
                </GuiDisplayTable>
                <GuiOutput id="160">
                  <PropertyList model="CTRL_GUI1_EDIT">
                    <Font id="50" val="101"/>
                    <Color id="51" val="101"/>
                  </PropertyList>
                </GuiOutput>
                <GuiOutputTable id="161">
                  <PropertyList model="CTRL_GUI1_EDIT">
                    <Font id="50" val="101"/>
                    <Color id="51" val="101"/>
                  </PropertyList>
                </GuiOutputTable>
                <NullValue id="167"/>
                <StoredAs id="173" val="1"/>
                <Definition id="175" val="2"/>
              </PropertyList>
            </Column>
            <Column id="7" name="D.システムバーコード識別">
              <PropertyList model="FIELD">
                <Model attr_obj="FIELD_ALPHA" comp="-1" id="1" obj="9"/>
                <StoredAs id="173" val="1"/>
                <Definition id="175" val="2"/>
              </PropertyList>
            </Column>
            <Column id="8" name="D.予備バーコード識別">
              <PropertyList model="FIELD">
                <Model attr_obj="FIELD_ALPHA" comp="-1" id="1" obj="9"/>
                <StoredAs id="173" val="1"/>
                <Definition id="175" val="2"/>
              </PropertyList>
            </Column>
            <Column id="9" name="DF.システムバーコード８桁許可">
              <PropertyList model="FIELD">
                <Model attr_obj="FIELD_LOGICAL" id="1"/>
                <GuiDisplay id="158">
                  <PropertyList model="CTRL_GUI0_EDIT">
                    <Font id="50" val="101"/>
                    <Color id="51" val="101"/>
                    <V11Style id="539" val="4"/>
                  </PropertyList>
                </GuiDisplay>
                <GuiDisplayTable id="159">
                  <PropertyList model="CTRL_GUI0_EDIT">
                    <Font id="50" val="101"/>
                    <Color id="51" val="101"/>
                  </PropertyList>
                </GuiDisplayTable>
                <GuiOutput id="160">
                  <PropertyList model="CTRL_GUI1_EDIT">
                    <Font id="50" val="101"/>
                    <Color id="51" val="101"/>
                  </PropertyList>
                </GuiOutput>
                <GuiOutputTable id="161">
                  <PropertyList model="CTRL_GUI1_EDIT">
                    <Font id="50" val="101"/>
                    <Color id="51" val="101"/>
                  </PropertyList>
                </GuiOutputTable>
                <NullValue id="167"/>
                <StoredAs id="173" val="1"/>
                <Definition id="175" val="2"/>
              </PropertyList>
            </Column>
            <Column id="10" name="DF.予備バーコード８桁許可">
              <PropertyList model="FIELD">
                <Model attr_obj="FIELD_LOGICAL" id="1"/>
                <GuiDisplay id="158">
                  <PropertyList model="CTRL_GUI0_EDIT">
                    <Font id="50" val="101"/>
                    <Color id="51" val="101"/>
                    <V11Style id="539" val="4"/>
                  </PropertyList>
                </GuiDisplay>
                <GuiDisplayTable id="159">
                  <PropertyList model="CTRL_GUI0_EDIT">
                    <Font id="50" val="101"/>
                    <Color id="51" val="101"/>
                  </PropertyList>
                </GuiDisplayTable>
                <GuiOutput id="160">
                  <PropertyList model="CTRL_GUI1_EDIT">
                    <Font id="50" val="101"/>
                    <Color id="51" val="101"/>
                  </PropertyList>
                </GuiOutput>
                <GuiOutputTable id="161">
                  <PropertyList model="CTRL_GUI1_EDIT">
                    <Font id="50" val="101"/>
                    <Color id="51" val="101"/>
                  </PropertyList>
                </GuiOutputTable>
                <NullValue id="167"/>
                <StoredAs id="173" val="1"/>
                <Definition id="175" val="2"/>
              </PropertyList>
            </Column>
            <Column id="11" name="w.CD">
              <PropertyList model="FIELD">
                <Model attr_obj="FIELD_ALPHA" id="1"/>
                <Picture id="157" valUnicode="1"/>
                <GuiDisplay id="158">
                  <PropertyList model="CTRL_GUI0_EDIT">
                    <Font id="50" val="101"/>
                    <Color id="51" val="101"/>
                    <V11Style id="539" val="4"/>
                  </PropertyList>
                </GuiDisplay>
                <GuiDisplayTable id="159">
                  <PropertyList model="CTRL_GUI0_EDIT">
                    <Font id="50" val="101"/>
                    <Color id="51" val="101"/>
                  </PropertyList>
                </GuiDisplayTable>
                <GuiOutput id="160">
                  <PropertyList model="CTRL_GUI1_EDIT">
                    <Font id="50" val="101"/>
                    <Color id="51" val="101"/>
                  </PropertyList>
                </GuiOutput>
                <GuiOutputTable id="161">
                  <PropertyList model="CTRL_GUI1_EDIT">
                    <Font id="50" val="101"/>
                    <Color id="51" val="101"/>
                  </PropertyList>
                </GuiOutputTable>
                <NullValue id="167"/>
                <StoredAs id="173" val="1"/>
                <Size id="174" val="1"/>
                <Definition id="175" val="2"/>
                <_Flip id="194"/>
              </PropertyList>
            </Column>
            <Column id="12" name="F.Tab Key">
              <PropertyList model="FIELD">
                <Model attr_obj="FIELD_LOGICAL" id="1"/>
                <GuiDisplay id="158">
                  <PropertyList model="CTRL_GUI0_EDIT">
                    <Font id="50" val="101"/>
                    <Color id="51" val="101"/>
                    <V11Style id="539" val="4"/>
                  </PropertyList>
                </GuiDisplay>
                <GuiDisplayTable id="159">
                  <PropertyList model="CTRL_GUI0_EDIT">
                    <Font id="50" val="101"/>
                    <Color id="51" val="101"/>
                  </PropertyList>
                </GuiDisplayTable>
                <GuiOutput id="160">
                  <PropertyList model="CTRL_GUI1_EDIT">
                    <Font id="50" val="101"/>
                    <Color id="51" val="101"/>
                  </PropertyList>
                </GuiOutput>
                <GuiOutputTable id="161">
                  <PropertyList model="CTRL_GUI1_EDIT">
                    <Font id="50" val="101"/>
                    <Color id="51" val="101"/>
                  </PropertyList>
                </GuiOutputTable>
                <NullValue id="167"/>
                <StoredAs id="173" val="1"/>
                <Definition id="175" val="2"/>
              </PropertyList>
            </Column>
            <Column id="13" name="sv.Barcd.顧客コード">
              <PropertyList model="FIELD">
                <Model attr_obj="FIELD_NUMERIC" comp="-1" id="1" obj="5"/>
                <StoredAs id="173"/>
                <DbColumnName id="178"/>
                <Type id="179"/>
                <UserType id="180"/>
              </PropertyList>
            </Column>
            <Column id="14" name="M.エージェント会社">
              <PropertyList model="FIELD">
                <Model attr_obj="FIELD_LOGICAL" id="1"/>
                <GuiDisplay id="158">
                  <PropertyList model="CTRL_GUI0_EDIT">
                    <Font id="50" val="101"/>
                    <Color id="51" val="101"/>
                    <V11Style id="539" val="4"/>
                  </PropertyList>
                </GuiDisplay>
                <GuiDisplayTable id="159">
                  <PropertyList model="CTRL_GUI0_EDIT">
                    <Font id="50" val="101"/>
                    <Color id="51" val="101"/>
                  </PropertyList>
                </GuiDisplayTable>
                <GuiOutput id="160">
                  <PropertyList model="CTRL_GUI1_EDIT">
                    <Font id="50" val="101"/>
                    <Color id="51" val="101"/>
                  </PropertyList>
                </GuiOutput>
                <GuiOutputTable id="161">
                  <PropertyList model="CTRL_GUI1_EDIT">
                    <Font id="50" val="101"/>
                    <Color id="51" val="101"/>
                  </PropertyList>
                </GuiOutputTable>
                <NullValue id="167"/>
                <StoredAs id="173" val="1"/>
                <Definition id="175" val="2"/>
              </PropertyList>
            </Column>
            <Column id="15" name="sv.Agent.顧客コード">
              <PropertyList model="FIELD">
                <Model attr_obj="FIELD_NUMERIC" comp="-1" id="1" obj="5"/>
                <StoredAs id="173"/>
                <DbColumnName id="178"/>
                <Type id="179"/>
                <UserType id="180"/>
              </PropertyList>
            </Column>
          </Columns>
        </Resource>
        <Information>
          <Key>
            <Mode val="N"/>
          </Key>
          <DB comp="-1"/>
          <Sort>
            <CLS val="A"/>
          </Sort>
          <ForceRecordDelete DEL="N"/>
          <EndTaskCondition val="Y"/>
          <EvaluateEndCondition val="A"/>
          <InitialMode val="M"/>
          <Locate Direction="A"/>
          <Range Direction="A"/>
          <VarRange/>
          <TaskProperties>
            <SelectionTable val="N"/>
            <ConfirmUpdate CNFU="N"/>
            <ConfirmCancel val="N"/>
            <ErrorStrategy val="A"/>
            <LockingStrategy val="I"/>
            <CacheStrategy val="N"/>
            <ForceRecordSuffix val="N"/>
            <TransactionMode val="P"/>
            <TransactionBegin val="N"/>
            <PreloadView val="N"/>
            <AllowEmptyDataview val="N"/>
            <KeepCreatedContext val="N"/>
          </TaskProperties>
          <SIDE_WIN>
            <AllowOptions val="N"/>
            <AllowQuery val="Y"/>
            <AllowModify val="Y"/>
            <AllowCreate val="Y"/>
            <AllowDelete val="N"/>
            <AllowLocate val="Y"/>
            <AllowRange val="Y"/>
            <AllowIndexChange val="Y"/>
            <AllowSorting val="Y"/>
            <AllowIOFiles val="Y"/>
            <RecordCycle val="N"/>
            <AllowEvents val="N"/>
            <AllowIndexOptimization val="Y"/>
            <AllowLocationInQuery val="Y"/>
            <AllowPrintingData val="N"/>
          </SIDE_WIN>
          <WIN>
            <OpenTaskWindow val="N"/>
            <CloseTaskWindow val="N"/>
            <ForegroundWindow val="N"/>
            <FlipFld val="N"/>
            <RefreshTaskWindow ReturnValue="N"/>
          </WIN>
          <BOX>
            <Right val="312"/>
            <Bottom val="160"/>
            <Direction val="V"/>
          </BOX>
        </Information>
        <TaskLogic>
          <LogicUnit id="2" propagate="78">
            <Level val="R"/>
            <Type val="M"/>
            <Scope val="S"/>
            <EngineDirective val="S"/>
            <ShowMessage val="Y"/>
            <Condition val="89"/>
            <Event>
              <EventType val="S"/>
              <PublicObject comp="-1"/>
            </Event>
            <Expanded val="1"/>
            <LogicLines>
              <LogicLine>
                <DATAVIEW_SRC FlowIsn="2" Type="M">
                  <Condition val="N"/>
                  <Modifier val="B"/>
                  <Direction val="C"/>
                </DATAVIEW_SRC>
              </LogicLine>
              <LogicLine>
                <Select FieldID="1" FlowIsn="3" id="1">
                  <Column val="1"/>
                  <Type val="V"/>
                  <IsParameter val="Y"/>
                  <DIFF_UPDATE val="T"/>
                  <Condition val="Y"/>
                  <Modifier val="S"/>
                  <Direction val="C"/>
                </Select>
              </LogicLine>
              <LogicLine>
                <Select FieldID="2" FlowIsn="4" id="2">
                  <Column val="2"/>
                  <Type val="V"/>
                  <IsParameter val="Y"/>
                  <DIFF_UPDATE val="T"/>
                  <Condition val="Y"/>
                  <Modifier val="S"/>
                  <Direction val="C"/>
                </Select>
              </LogicLine>
              <LogicLine>
                <Select FieldID="3" FlowIsn="5" id="3">
                  <Column val="3"/>
                  <Type val="V"/>
                  <IsParameter val="Y"/>
                  <DIFF_UPDATE val="T"/>
                  <Condition val="Y"/>
                  <Modifier val="S"/>
                  <Direction val="C"/>
                </Select>
              </LogicLine>
              <LogicLine>
                <Select FieldID="4" FlowIsn="6" id="4">
                  <Column val="4"/>
                  <Type val="V"/>
                  <IsParameter val="Y"/>
                  <DIFF_UPDATE val="T"/>
                  <Condition val="Y"/>
                  <Modifier val="S"/>
                  <Direction val="C"/>
                </Select>
              </LogicLine>
              <LogicLine>
                <Select FieldID="5" FlowIsn="7" id="5">
                  <Column val="5"/>
                  <Type val="V"/>
                  <IsParameter val="Y"/>
                  <DIFF_UPDATE val="T"/>
                  <Condition val="Y"/>
                  <Modifier val="S"/>
                  <Direction val="C"/>
                </Select>
              </LogicLine>
              <LogicLine>
                <Select FieldID="6" FlowIsn="8" id="6">
                  <Column val="6"/>
                  <Type val="V"/>
                  <IsParameter val="Y"/>
                  <DIFF_UPDATE val="T"/>
                  <Condition val="Y"/>
                  <Modifier val="S"/>
                  <Direction val="C"/>
                </Select>
              </LogicLine>
              <LogicLine>
                <Remark FlowIsn="9">
                  <Type val="0"/>
                  <Text val=" "/>
                </Remark>
              </LogicLine>
              <LogicLine>
                <Select FieldID="7" FlowIsn="10" id="7">
                  <Column val="7"/>
                  <Type val="V"/>
                  <IsParameter val="N"/>
                  <DIFF_UPDATE val="T"/>
                  <Condition val="Y"/>
                  <Modifier val="S"/>
                  <Direction val="C"/>
                </Select>
              </LogicLine>
              <LogicLine>
                <Select FieldID="8" FlowIsn="11" id="8">
                  <Column val="8"/>
                  <Type val="V"/>
                  <IsParameter val="N"/>
                  <DIFF_UPDATE val="T"/>
                  <Condition val="Y"/>
                  <Modifier val="S"/>
                  <Direction val="C"/>
                </Select>
              </LogicLine>
              <LogicLine>
                <Select FieldID="9" FlowIsn="12" id="9">
                  <Column val="9"/>
                  <Type val="V"/>
                  <IsParameter val="N"/>
                  <DIFF_UPDATE val="T"/>
                  <Condition val="Y"/>
                  <Modifier val="S"/>
                  <Direction val="C"/>
                </Select>
              </LogicLine>
              <LogicLine>
                <Select FieldID="10" FlowIsn="13" id="10">
                  <Column val="10"/>
                  <Type val="V"/>
                  <IsParameter val="N"/>
                  <DIFF_UPDATE val="T"/>
                  <Condition val="Y"/>
                  <Modifier val="S"/>
                  <Direction val="C"/>
                </Select>
              </LogicLine>
              <LogicLine>
                <Remark FlowIsn="14">
                  <Type val="0"/>
                  <Text val=" "/>
                </Remark>
              </LogicLine>
              <LogicLine>
                <Select FieldID="11" FlowIsn="15" id="11">
                  <Column val="11"/>
                  <Type val="V"/>
                  <IsParameter val="N"/>
                  <DIFF_UPDATE val="T"/>
                  <Condition val="Y"/>
                  <Modifier val="S"/>
                  <Direction val="C"/>
                </Select>
              </LogicLine>
              <LogicLine>
                <Select FieldID="12" FlowIsn="16" id="12">
                  <Column val="12"/>
                  <Type val="V"/>
                  <IsParameter val="N"/>
                  <DIFF_UPDATE val="T"/>
                  <Condition val="Y"/>
                  <Modifier val="S"/>
                  <Direction val="C"/>
                </Select>
              </LogicLine>
              <LogicLine>
                <Remark FlowIsn="17">
                  <Type val="0"/>
                  <Text val=" "/>
                </Remark>
              </LogicLine>
              <LogicLine>
                <Select FieldID="13" FlowIsn="18" id="13">
                  <Column val="13"/>
                  <Type val="V"/>
                  <IsParameter val="N"/>
                  <DIFF_UPDATE val="T"/>
                  <Condition val="Y"/>
                  <Modifier val="S"/>
                  <Direction val="C"/>
                </Select>
              </LogicLine>
              <LogicLine>
                <Remark FlowIsn="19">
                  <Type val="0"/>
                  <Text val=" "/>
                </Remark>
              </LogicLine>
              <LogicLine>
                <Select FieldID="14" FlowIsn="20" id="14">
                  <Column val="14"/>
                  <Type val="V"/>
                  <IsParameter val="N"/>
                  <DIFF_UPDATE val="T"/>
                  <Condition val="Y"/>
                  <Modifier val="S"/>
                  <Direction val="C"/>
                </Select>
              </LogicLine>
              <LogicLine>
                <Select FieldID="15" FlowIsn="21" id="15">
                  <Column val="15"/>
                  <Type val="V"/>
                  <IsParameter val="N"/>
                  <Locate MAX="13" MIN="13"/>
                  <DIFF_UPDATE val="T"/>
                  <Condition val="Y"/>
                  <Modifier val="S"/>
                  <Direction val="C"/>
                </Select>
              </LogicLine>
            </LogicLines>
          </LogicUnit>
          <LogicUnit id="3" propagate="78">
            <Level val="T"/>
            <Type val="P"/>
            <Scope val="S"/>
            <EngineDirective val="S"/>
            <ShowMessage val="Y"/>
            <Condition val="89"/>
            <Event>
              <EventType val="S"/>
              <PublicObject comp="-1"/>
            </Event>
            <Expanded val="1"/>
            <LogicLines>
              <LogicLine>
                <Remark FlowIsn="22">
                  <Type val="2"/>
                  <Text val="// 初期化"/>
                </Remark>
              </LogicLine>
              <LogicLine>
                <Update FlowIsn="23">
                  <FieldID val="2"/>
                  <WithValue val="4"/>
                  <Incremental val="N"/>
                  <ForcedUpdate val="Y"/>
                  <Condition val="Y"/>
                  <Modifier val="B"/>
                  <Direction val="C"/>
                </Update>
              </LogicLine>
              <LogicLine>
                <Update FlowIsn="24">
                  <FieldID val="4"/>
                  <WithValue val="5"/>
                  <Incremental val="N"/>
                  <ForcedUpdate val="Y"/>
                  <Condition val="Y"/>
                  <Modifier val="B"/>
                  <Direction val="C"/>
                </Update>
              </LogicLine>
              <LogicLine>
                <Update FlowIsn="25">
                  <FieldID val="5"/>
                  <WithValue val="6"/>
                  <Incremental val="N"/>
                  <ForcedUpdate val="Y"/>
                  <Condition val="Y"/>
                  <Modifier val="B"/>
                  <Direction val="C"/>
                </Update>
              </LogicLine>
              <LogicLine>
                <Remark FlowIsn="26">
                  <Type val="2"/>
                  <Text val="// エージェント対応 2004/05/10"/>
                </Remark>
              </LogicLine>
              <LogicLine>
                <Update FlowIsn="27">
                  <FieldID val="6"/>
                  <WithValue val="7"/>
                  <Incremental val="N"/>
                  <ForcedUpdate val="Y"/>
                  <Condition val="Y"/>
                  <Modifier val="B"/>
                  <Direction val="C"/>
                </Update>
              </LogicLine>
              <LogicLine>
                <Remark FlowIsn="28">
                  <Type val="2"/>
                  <Text val=" "/>
                </Remark>
              </LogicLine>
              <LogicLine>
                <Update FlowIsn="29">
                  <FieldID val="12"/>
                  <WithValue val="8"/>
                  <Incremental val="N"/>
                  <ForcedUpdate val="Y"/>
                  <Condition val="Y"/>
                  <Modifier val="B"/>
                  <Direction val="C"/>
                </Update>
              </LogicLine>
              <LogicLine>
                <Remark FlowIsn="30">
                  <Type val="2"/>
                  <Text val=" "/>
                </Remark>
              </LogicLine>
              <LogicLine>
                <Remark FlowIsn="31">
                  <Type val="2"/>
                  <Text val="// 顧客システムバーコード取得"/>
                </Remark>
              </LogicLine>
              <LogicLine>
                <CallTask FlowIsn="32">
                  <OperationType val="P"/>
                  <TaskID comp="-1" obj="921"/>
                  <Lock val="Y"/>
                  <Arguments>
                    <Argument>
                      <Expression val="1"/>
                      <Skip val="N"/>
                    </Argument>
                    <Argument>
                      <Expression val="2"/>
                      <Skip val="N"/>
                    </Argument>
                    <Argument>
                      <Variable val="7"/>
                      <Skip val="N"/>
                    </Argument>
                    <Argument>
                      <Variable val="9"/>
                      <Skip val="N"/>
                    </Argument>
                  </Arguments>
                  <Wait val="Y"/>
                  <SyncData val="N"/>
                  <RetainFocus val="N"/>
                  <Condition val="Y"/>
                  <Modifier val="B"/>
                  <Direction val="C"/>
                </CallTask>
              </LogicLine>
              <LogicLine>
                <Update FlowIsn="33">
                  <FieldID val="7"/>
                  <WithValue val="9"/>
                  <Incremental val="N"/>
                  <ForcedUpdate val="Y"/>
                  <Condition Exp="10"/>
                  <Modifier val="B"/>
                  <Direction val="C"/>
                </Update>
              </LogicLine>
              <LogicLine>
                <Remark FlowIsn="34">
                  <Type val="2"/>
                  <Text val=" "/>
                </Remark>
              </LogicLine>
              <LogicLine>
                <Remark FlowIsn="35">
                  <Type val="2"/>
                  <Text val="// 顧客バーコード予備取得"/>
                </Remark>
              </LogicLine>
              <LogicLine>
                <CallTask FlowIsn="36">
                  <OperationType val="P"/>
                  <TaskID comp="-1" obj="921"/>
                  <Lock val="Y"/>
                  <Arguments>
                    <Argument>
                      <Expression val="1"/>
                      <Skip val="N"/>
                    </Argument>
                    <Argument>
                      <Expression val="3"/>
                      <Skip val="N"/>
                    </Argument>
                    <Argument>
                      <Variable val="8"/>
                      <Skip val="N"/>
                    </Argument>
                    <Argument>
                      <Variable val="10"/>
                      <Skip val="N"/>
                    </Argument>
                  </Arguments>
                  <Wait val="Y"/>
                  <SyncData val="N"/>
                  <RetainFocus val="N"/>
                  <Condition val="Y"/>
                  <Modifier val="B"/>
                  <Direction val="C"/>
                </CallTask>
              </LogicLine>
              <LogicLine>
                <Remark FlowIsn="37">
                  <Type val="2"/>
                  <Text val=" "/>
                </Remark>
              </LogicLine>
              <LogicLine>
                <Remark FlowIsn="38">
                  <Type val="2"/>
                  <Text val=" "/>
                </Remark>
              </LogicLine>
              <LogicLine>
                <BLOCK EndBlock="44" EndBlockSegment="42" FlowIsn="39" Type="I">
                  <Condition Exp="11"/>
                  <Modifier val="B"/>
                  <Direction val="C"/>
                </BLOCK>
              </LogicLine>
              <LogicLine>
                <CallTask FlowIsn="40">
                  <OperationType val="T"/>
                  <TaskID comp="-1" obj="3"/>
                  <Lock val="N"/>
                  <Wait val="Y"/>
                  <SyncData val="N"/>
                  <RetainFocus val="N"/>
                  <Condition val="Y"/>
                  <Modifier val="B"/>
                  <Direction val="C"/>
                </CallTask>
              </LogicLine>
              <LogicLine>
                <Remark FlowIsn="41">
                  <Type val="2"/>
                  <Text val=" "/>
                </Remark>
              </LogicLine>
              <LogicLine>
                <BLOCK EndBlock="44" EndBlockSegment="44" FlowIsn="42" Type="E">
                  <Condition val="Y"/>
                  <Modifier val="B"/>
                  <Direction val="C"/>
                </BLOCK>
              </LogicLine>
              <LogicLine>
                <CallTask FlowIsn="43">
                  <OperationType val="T"/>
                  <TaskID comp="-1" obj="2"/>
                  <Lock val="N"/>
                  <Wait val="Y"/>
                  <SyncData val="N"/>
                  <RetainFocus val="N"/>
                  <Condition val="Y"/>
                  <Modifier val="B"/>
                  <Direction val="C"/>
                </CallTask>
              </LogicLine>
              <LogicLine>
                <END_BLK FlowIsn="44"/>
              </LogicLine>
            </LogicLines>
          </LogicUnit>
          <LogicUnit id="4" propagate="78">
            <Level val="T"/>
            <Type val="S"/>
            <Scope val="S"/>
            <EngineDirective val="S"/>
            <ShowMessage val="Y"/>
            <Condition val="89"/>
            <Event>
              <EventType val="S"/>
              <PublicObject comp="-1"/>
            </Event>
            <Expanded val="1"/>
          </LogicUnit>
          <LogicUnit id="5" propagate="78">
            <Level val="R"/>
            <Type val="P"/>
            <Scope val="S"/>
            <EngineDirective val="S"/>
            <ShowMessage val="Y"/>
            <Condition val="89"/>
            <Event>
              <EventType val="S"/>
              <PublicObject comp="-1"/>
            </Event>
            <Expanded val="1"/>
          </LogicUnit>
          <LogicUnit id="6" propagate="78">
            <Level val="R"/>
            <Type val="S"/>
            <Scope val="S"/>
            <EngineDirective val="S"/>
            <ShowMessage val="Y"/>
            <Condition val="89"/>
            <Event>
              <EventType val="S"/>
              <PublicObject comp="-1"/>
            </Event>
            <Expanded val="1"/>
            <LogicLines>
              <LogicLine>
                <Remark FlowIsn="45">
                  <Type val="2"/>
                  <Text val="// ８桁バーコードだったら１３桁に変換しちゃう"/>
                </Remark>
              </LogicLine>
              <LogicLine>
                <BLOCK EndBlock="48" EndBlockSegment="48" FlowIsn="46" Type="I">
                  <Condition Exp="14"/>
                  <Modifier val="B"/>
                  <Direction val="C"/>
                </BLOCK>
              </LogicLine>
              <LogicLine>
                <RaiseEvent FlowIsn="47">
                  <Event>
                    <EventType val="U"/>
                    <PublicObject comp="-1" obj="1"/>
                  </Event>
                  <Wait val="89"/>
                  <Condition val="Y"/>
                  <Modifier val="B"/>
                  <Direction val="C"/>
                </RaiseEvent>
              </LogicLine>
              <LogicLine>
                <END_BLK FlowIsn="48"/>
              </LogicLine>
              <LogicLine>
                <Remark FlowIsn="49">
                  <Type val="2"/>
                  <Text val=" "/>
                </Remark>
              </LogicLine>
              <LogicLine>
                <Remark FlowIsn="50">
                  <Type val="2"/>
                  <Text val="◆ システムバーコードスキャン"/>
                </Remark>
              </LogicLine>
              <LogicLine>
                <BLOCK EndBlock="68" EndBlockSegment="56" FlowIsn="51" Type="I">
                  <Condition Exp="17"/>
                  <Modifier val="B"/>
                  <Direction val="C"/>
                </BLOCK>
              </LogicLine>
              <LogicLine>
                <Update FlowIsn="52">
                  <FieldID val="1"/>
                  <WithValue val="18"/>
                  <Incremental val="N"/>
                  <ForcedUpdate val="Y"/>
                  <Condition val="Y"/>
                  <Modifier val="B"/>
                  <Direction val="C"/>
                </Update>
              </LogicLine>
              <LogicLine>
                <Update FlowIsn="53">
                  <FieldID val="2"/>
                  <WithValue val="12"/>
                  <Incremental val="N"/>
                  <ForcedUpdate val="Y"/>
                  <Condition val="Y"/>
                  <Modifier val="B"/>
                  <Direction val="C"/>
                </Update>
              </LogicLine>
              <LogicLine>
                <Remark FlowIsn="54">
                  <Type val="2"/>
                  <Text val=" "/>
                </Remark>
              </LogicLine>
              <LogicLine>
                <Remark FlowIsn="55">
                  <Type val="2"/>
                  <Text val="◆ 顧客システムバーコード(設定値)"/>
                </Remark>
              </LogicLine>
              <LogicLine>
                <BLOCK EndBlock="68" EndBlockSegment="66" FlowIsn="56" Type="E">
                  <Condition Exp="19"/>
                  <Modifier val="B"/>
                  <Direction val="C"/>
                </BLOCK>
              </LogicLine>
              <LogicLine>
                <CallTask FlowIsn="57">
                  <OperationType val="P"/>
                  <TaskID comp="-1" obj="853"/>
                  <Lock val="N"/>
                  <Arguments>
                    <Argument>
                      <Variable val="1"/>
                      <Skip val="N"/>
                    </Argument>
                    <Argument>
                      <Variable val="11"/>
                      <Skip val="N"/>
                    </Argument>
                  </Arguments>
                  <Wait val="Y"/>
                  <SyncData val="N"/>
                  <RetainFocus val="N"/>
                  <Condition val="Y"/>
                  <Modifier val="B"/>
                  <Direction val="C"/>
                </CallTask>
              </LogicLine>
              <LogicLine>
                <BLOCK EndBlock="60" EndBlockSegment="60" FlowIsn="58" Type="I">
                  <Condition Exp="20"/>
                  <Modifier val="B"/>
                  <Direction val="C"/>
                </BLOCK>
              </LogicLine>
              <LogicLine>
                <Update FlowIsn="59">
                  <FieldID val="1"/>
                  <WithValue val="21"/>
                  <Incremental val="N"/>
                  <ForcedUpdate val="Y"/>
                  <Condition val="Y"/>
                  <Modifier val="B"/>
                  <Direction val="C"/>
                </Update>
              </LogicLine>
              <LogicLine>
                <END_BLK FlowIsn="60"/>
              </LogicLine>
              <LogicLine>
                <Update FlowIsn="61">
                  <FieldID val="5"/>
                  <WithValue val="22"/>
                  <Incremental val="N"/>
                  <ForcedUpdate val="Y"/>
                  <Condition val="Y"/>
                  <Modifier val="B"/>
                  <Direction val="C"/>
                </Update>
              </LogicLine>
              <LogicLine>
                <Update FlowIsn="62">
                  <FieldID val="2"/>
                  <WithValue val="23"/>
                  <Incremental val="N"/>
                  <ForcedUpdate val="Y"/>
                  <Condition val="Y"/>
                  <Modifier val="B"/>
                  <Direction val="C"/>
                </Update>
              </LogicLine>
              <LogicLine>
                <Update FlowIsn="63">
                  <FieldID val="1"/>
                  <WithValue val="24"/>
                  <Incremental val="N"/>
                  <ForcedUpdate val="Y"/>
                  <Condition val="Y"/>
                  <Modifier val="B"/>
                  <Direction val="C"/>
                </Update>
              </LogicLine>
              <LogicLine>
                <Remark FlowIsn="64">
                  <Type val="2"/>
                  <Text val=" "/>
                </Remark>
              </LogicLine>
              <LogicLine>
                <Remark FlowIsn="65">
                  <Type val="2"/>
                  <Text val="◆ 顧客コードでもなく、顧客バーコードでもない（11桁以上）"/>
                </Remark>
              </LogicLine>
              <LogicLine>
                <BLOCK EndBlock="68" EndBlockSegment="68" FlowIsn="66" Type="E">
                  <Condition Exp="25"/>
                  <Modifier val="B"/>
                  <Direction val="C"/>
                </BLOCK>
              </LogicLine>
              <LogicLine>
                <Update FlowIsn="67">
                  <FieldID val="4"/>
                  <WithValue val="26"/>
                  <Incremental val="N"/>
                  <ForcedUpdate val="Y"/>
                  <Condition val="Y"/>
                  <Modifier val="B"/>
                  <Direction val="C"/>
                </Update>
              </LogicLine>
              <LogicLine>
                <END_BLK FlowIsn="68"/>
              </LogicLine>
              <LogicLine>
                <Remark FlowIsn="69">
                  <Type val="2"/>
                  <Text val=" "/>
                </Remark>
              </LogicLine>
              <LogicLine>
                <Remark FlowIsn="70">
                  <Type val="2"/>
                  <Text val=" "/>
                </Remark>
              </LogicLine>
              <LogicLine>
                <Remark FlowIsn="71">
                  <Type val="2"/>
                  <Text val="◆ スキャンコードエラーだったら"/>
                </Remark>
              </LogicLine>
              <LogicLine>
                <BLOCK EndBlock="84" EndBlockSegment="75" FlowIsn="72" Type="I">
                  <Condition Exp="27"/>
                  <Modifier val="B"/>
                  <Direction val="C"/>
                </BLOCK>
              </LogicLine>
              <LogicLine>
                <Remark FlowIsn="73">
                  <Type val="2"/>
                  <Text val=" "/>
                </Remark>
              </LogicLine>
              <LogicLine>
                <Remark FlowIsn="74">
                  <Type val="2"/>
                  <Text val="◆ スキャンコードエラーでなかったら"/>
                </Remark>
              </LogicLine>
              <LogicLine>
                <BLOCK EndBlock="84" EndBlockSegment="84" FlowIsn="75" Type="E">
                  <Condition val="Y"/>
                  <Modifier val="B"/>
                  <Direction val="C"/>
                </BLOCK>
              </LogicLine>
              <LogicLine>
                <Remark FlowIsn="76">
                  <Type val="2"/>
                  <Text val="  ◇ エージェント用チェック(Agent管理時のみ)"/>
                </Remark>
              </LogicLine>
              <LogicLine>
                <RaiseEvent FlowIsn="77">
                  <Event>
                    <EventType val="U"/>
                    <PublicObject comp="-1" obj="2"/>
                  </Event>
                  <Wait val="89"/>
                  <Condition Exp="28"/>
                  <Modifier val="B"/>
                  <Direction val="C"/>
                </RaiseEvent>
              </LogicLine>
              <LogicLine>
                <Remark FlowIsn="78">
                  <Type val="2"/>
                  <Text val=" "/>
                </Remark>
              </LogicLine>
              <LogicLine>
                <BLOCK EndBlock="82" EndBlockSegment="82" FlowIsn="79" Type="I">
                  <Condition Exp="31"/>
                  <Modifier val="B"/>
                  <Direction val="C"/>
                </BLOCK>
              </LogicLine>
              <LogicLine>
                <Update FlowIsn="80">
                  <FieldID val="2"/>
                  <WithValue val="12"/>
                  <Incremental val="N"/>
                  <ForcedUpdate val="Y"/>
                  <Condition val="Y"/>
                  <Modifier val="B"/>
                  <Direction val="C"/>
                </Update>
              </LogicLine>
              <LogicLine>
                <Update FlowIsn="81">
                  <FieldID val="1"/>
                  <WithValue val="24"/>
                  <Incremental val="N"/>
                  <ForcedUpdate val="Y"/>
                  <Condition val="Y"/>
                  <Modifier val="B"/>
                  <Direction val="C"/>
                </Update>
              </LogicLine>
              <LogicLine>
                <END_BLK FlowIsn="82"/>
              </LogicLine>
              <LogicLine>
                <Remark FlowIsn="83">
                  <Type val="2"/>
                  <Text val=" "/>
                </Remark>
              </LogicLine>
              <LogicLine>
                <END_BLK FlowIsn="84"/>
              </LogicLine>
            </LogicLines>
          </LogicUnit>
          <LogicUnit id="7" propagate="78">
            <Level val="H"/>
            <Type val="U"/>
            <Scope val="T"/>
            <EngineDirective val="S"/>
            <ShowMessage val="Y"/>
            <Condition val="89"/>
            <Event>
              <EventType val="U"/>
              <PublicObject comp="-1" obj="1"/>
            </Event>
            <Expanded val="1"/>
            <LogicLines>
              <LogicLine>
                <Update FlowIsn="85">
                  <FieldID val="1"/>
                  <WithValue val="15"/>
                  <Incremental val="N"/>
                  <ForcedUpdate val="Y"/>
                  <Condition val="Y"/>
                  <Modifier val="B"/>
                  <Direction val="C"/>
                </Update>
              </LogicLine>
              <LogicLine>
                <CallTask FlowIsn="86">
                  <OperationType val="P"/>
                  <TaskID comp="-1" obj="853"/>
                  <Lock val="Y"/>
                  <Arguments>
                    <Argument>
                      <Variable val="1"/>
                      <Skip val="N"/>
                    </Argument>
                    <Argument>
                      <Variable val="11"/>
                      <Skip val="N"/>
                    </Argument>
                  </Arguments>
                  <Wait val="Y"/>
                  <SyncData val="N"/>
                  <RetainFocus val="N"/>
                  <Condition val="Y"/>
                  <Modifier val="B"/>
                  <Direction val="C"/>
                </CallTask>
              </LogicLine>
              <LogicLine>
                <Update FlowIsn="87">
                  <FieldID val="1"/>
                  <WithValue val="16"/>
                  <Incremental val="N"/>
                  <ForcedUpdate val="Y"/>
                  <Condition val="Y"/>
                  <Modifier val="B"/>
                  <Direction val="C"/>
                </Update>
              </LogicLine>
            </LogicLines>
          </LogicUnit>
          <LogicUnit id="8" propagate="78">
            <Level val="H"/>
            <Type val="U"/>
            <Scope val="T"/>
            <EngineDirective val="S"/>
            <ShowMessage val="Y"/>
            <Condition val="89"/>
            <Event>
              <EventType val="U"/>
              <PublicObject comp="-1" obj="2"/>
            </Event>
            <Expanded val="1"/>
            <LogicLines>
              <LogicLine>
                <Remark FlowIsn="88">
                  <Type val="2"/>
                  <Text val="// ☆ ツアーコードで、エージェント会社が未登録だったら"/>
                </Remark>
              </LogicLine>
              <LogicLine>
                <BLOCK EndBlock="91" EndBlockSegment="91" FlowIsn="89" Type="I">
                  <Condition Exp="29"/>
                  <Modifier val="B"/>
                  <Direction val="C"/>
                </BLOCK>
              </LogicLine>
              <LogicLine>
                <Update FlowIsn="90">
                  <FieldID val="6"/>
                  <WithValue val="30"/>
                  <Incremental val="N"/>
                  <ForcedUpdate val="Y"/>
                  <Condition val="Y"/>
                  <Modifier val="B"/>
                  <Direction val="C"/>
                </Update>
              </LogicLine>
              <LogicLine>
                <END_BLK FlowIsn="91"/>
              </LogicLine>
            </LogicLines>
          </LogicUnit>
        </TaskLogic>
        <TaskForms>
          <FormEntry id="1">
            <PropertyList model="FORM_GUI0">
              <Width id="23" val="366"/>
              <Height id="24" val="231"/>
              <GridX id="38" val="5"/>
              <GridY id="39" val="9"/>
              <Font id="50" val="121"/>
              <Color id="51" val="101"/>
              <_Comment id="218"/>
              <FormName id="311" valUnicode="  S.顧客コード判定(both)"/>
              <_TabbingOrder id="318" val="1"/>
              <WindowType id="358" val="1"/>
              <PersistentFormState id="493"/>
            </PropertyList>
          </FormEntry>
        </TaskForms>
        <Expressions>
          <Expression id="1">
            <ExpSyntax val="2"/>
            <ExpAttribute val="N"/>
          </Expression>
          <Expression id="2">
            <ExpSyntax val="0"/>
            <ExpAttribute val="N"/>
          </Expression>
          <Expression id="3">
            <ExpSyntax val="1"/>
            <ExpAttribute val="N"/>
          </Expression>
          <Expression id="4">
            <ExpSyntax val="0"/>
            <ExpAttribute val="N"/>
          </Expression>
          <Expression id="5">
            <ExpSyntax val="'FALSE'LOG"/>
            <ExpAttribute val="B"/>
          </Expression>
          <Expression id="6">
            <ExpSyntax val="''"/>
            <ExpAttribute val="A"/>
          </Expression>
          <Expression id="7">
            <ExpSyntax val="'FALSE'LOG"/>
            <ExpAttribute val="B"/>
          </Expression>
          <Expression id="8">
            <ExpSyntax val="KbGet (0)='Tab'KBD"/>
            <ExpAttribute val="B"/>
          </Expression>
          <Expression id="9">
            <ExpSyntax val="'21'"/>
            <ExpAttribute val="A"/>
          </Expression>
          <Expression id="10">
            <ExpSyntax val="{0,7}=''"/>
            <ExpAttribute val="B"/>
          </Expression>
          <Expression id="11">
            <ExpSyntax val="{32768,94} AND {0,3}"/>
            <ExpAttribute val="B"/>
          </Expression>
          <Expression id="12">
            <ExpSyntax val="Val (Left (Trim ({0,1}),10),'10P0Z')"/>
            <ExpAttribute val="N"/>
          </Expression>
          <Expression id="13">
            <ExpSyntax val="Val (Left (Trim ({0,1}),Len (Trim ({0,1}))-{32768,170}),'10P0Z')*10^{32768,170}"/>
            <ExpAttribute val="N"/>
          </Expression>
          <Expression id="14">
            <ExpSyntax val="{0,12} AND ({0,9} AND Left ({0,1},Len (Trim ({0,7})))=Trim ({0,7}) AND Range (Len (RTrim ({0,1})),7,8) OR {0,10} AND Left ({0,1},Len (Trim ({0,8})))=Trim ({0,8}) AND Range (Len (RTrim ({0,1})),7,8))"/>
            <ExpAttribute val="B"/>
          </Expression>
          <Expression id="15">
            <ExpSyntax val="Left ({0,1},2)&amp;'00000'&amp;MID ({0,1},3,5)"/>
            <ExpAttribute val="A"/>
          </Expression>
          <Expression id="16">
            <ExpSyntax val="Left ({0,1},12)&amp;{0,11}"/>
            <ExpAttribute val="A"/>
          </Expression>
          <Expression id="17">
            <ExpSyntax val="Left ({0,1},Len (Trim ({0,7})))=Trim ({0,7}) AND Range (Len (RTrim ({0,1})),12,13)"/>
            <ExpAttribute val="B"/>
          </Expression>
          <Expression id="18">
            <ExpSyntax val="Str (Val (MID ({0,1},3,10),'10P0Z0'),'10P0Z')"/>
            <ExpAttribute val="A"/>
          </Expression>
          <Expression id="19">
            <ExpSyntax val="{0,8}&lt;>'' AND Left ({0,1},Len (Trim ({0,8})))=Trim ({0,8}) AND Len (Trim ({0,1}))>10"/>
            <ExpAttribute val="B"/>
          </Expression>
          <Expression id="20">
            <ExpSyntax val="Right (RTrim ({0,1}),1)&lt;>{0,11}"/>
            <ExpAttribute val="B"/>
          </Expression>
          <Expression id="21">
            <ExpSyntax val="Left (RTrim ({0,1}),IF (Range (Len (RTrim ({0,1})),7,8),7,12))&amp;{0,11}"/>
            <ExpAttribute val="A"/>
          </Expression>
          <Expression id="22">
            <ExpSyntax val="{0,1}"/>
            <ExpAttribute val="A"/>
          </Expression>
          <Expression id="23">
            <ExpSyntax val="{0,13}"/>
            <ExpAttribute val="N"/>
          </Expression>
          <Expression id="24">
            <ExpSyntax val="Str ({0,2},'10P0Z')"/>
            <ExpAttribute val="A"/>
          </Expression>
          <Expression id="25">
            <ExpSyntax val="Len (RTrim ({0,1}))>10"/>
            <ExpAttribute val="B"/>
          </Expression>
          <Expression id="26">
            <ExpSyntax val="'TRUE'LOG"/>
            <ExpAttribute val="B"/>
          </Expression>
          <Expression id="27">
            <ExpSyntax val="{0,4}"/>
            <ExpAttribute val="B"/>
          </Expression>
          <Expression id="28">
            <ExpSyntax val="{32768,169} AND Range (Val (Left (Trim ({0,1}),10),'10P0Z'),{32768,171},{32768,172})"/>
            <ExpAttribute val="B"/>
          </Expression>
          <Expression id="29">
            <ExpSyntax val="Val (Right (RTrim ({0,1}),{32768,170}),Str ({32768,170},'2P0Z0')&amp;'P0Z')&lt;>0 AND (NOT ({0,14}) OR {0,15}=0)"/>
            <ExpAttribute val="B"/>
          </Expression>
          <Expression id="30">
            <ExpSyntax val="'TRUE'LOG"/>
            <ExpAttribute val="B"/>
          </Expression>
          <Expression id="31">
            <ExpSyntax val="NOT ({0,6})"/>
            <ExpAttribute val="B"/>
          </Expression>
        </Expressions>
        <EVNT DESC="Levt_８桁バースキャン" FORCE_EXIT="N" id="1">
          <Event>
            <EventType val="N"/>
            <PublicObject comp="-1"/>
          </Event>
        </EVNT>
        <EVNT DESC="Levt_エージェント用" FORCE_EXIT="N" id="2">
          <Event>
            <EventType val="N"/>
            <PublicObject comp="-1"/>
          </Event>
        </EVNT>
        <Task MainProgram="N">
          <Header Description="値取得(pvsw)" ISN_2="2" id="372">
            <ExecutionRight comp="-1"/>
            <Resident val="N"/>
            <SQL val="N"/>
            <ReturnValue>
              <ReturnValueAttr/>
              <ParametersAttributes/>
            </ReturnValue>
            <SqlWhereExist val="N"/>
            <TaskType val="B"/>
            <External val="N"/>
            <FormType val="N"/>
            <DotNetObjectExists val="N"/>
            <LastModified _date="733849" _time="40540" date="2010/03/18" time="11:15:40"/>
          </Header>
          <ItemIsn val="4"/>
          <Resource>
            <DB id="1">
              <DataObject comp="-1" obj="4"/>
              <Access val="R"/>
              <Share val="W"/>
              <Open val="N"/>
              <Cache val="N"/>
              <IdentifyRowModifications val="84"/>
            </DB>
            <Columns>
              <Column id="1" name="M.エージェント会社">
                <PropertyList model="FIELD">
                  <Model attr_obj="FIELD_LOGICAL" id="1"/>
                  <GuiDisplay id="158">
                    <PropertyList model="CTRL_GUI0_EDIT">
                      <Font id="50" val="101"/>
                      <Color id="51" val="101"/>
                      <V11Style id="539" val="4"/>
                    </PropertyList>
                  </GuiDisplay>
                  <GuiDisplayTable id="159">
                    <PropertyList model="CTRL_GUI0_EDIT">
                      <Font id="50" val="101"/>
                      <Color id="51" val="101"/>
                    </PropertyList>
                  </GuiDisplayTable>
                  <GuiOutput id="160">
                    <PropertyList model="CTRL_GUI1_EDIT">
                      <Font id="50" val="101"/>
                      <Color id="51" val="101"/>
                    </PropertyList>
                  </GuiOutput>
                  <GuiOutputTable id="161">
                    <PropertyList model="CTRL_GUI1_EDIT">
                      <Font id="50" val="101"/>
                      <Color id="51" val="101"/>
                    </PropertyList>
                  </GuiOutputTable>
                  <NullValue id="167"/>
                  <StoredAs id="173" val="1"/>
                  <Definition id="175" val="2"/>
                </PropertyList>
              </Column>
            </Columns>
          </Resource>
          <Information>
            <Key>
              <Mode val="N"/>
            </Key>
            <DB comp="-1"/>
            <Sort>
              <CLS val="A"/>
            </Sort>
            <ForceRecordDelete DEL="N"/>
            <EndTaskCondition val="Y"/>
            <EvaluateEndCondition val="A"/>
            <InitialMode val="M"/>
            <Locate Direction="A"/>
            <Range Direction="A"/>
            <VarRange/>
            <TaskProperties>
              <SelectionTable val="N"/>
              <ConfirmUpdate CNFU="N"/>
              <ConfirmCancel val="N"/>
              <ErrorStrategy val="A"/>
              <LockingStrategy val="I"/>
              <CacheStrategy val="N"/>
              <ForceRecordSuffix val="N"/>
              <TransactionMode val="P"/>
              <TransactionBegin val="T"/>
              <PreloadView val="N"/>
              <AllowEmptyDataview val="N"/>
              <KeepCreatedContext val="N"/>
            </TaskProperties>
            <SIDE_WIN>
              <AllowOptions val="N"/>
              <AllowQuery val="Y"/>
              <AllowModify val="Y"/>
              <AllowCreate val="Y"/>
              <AllowDelete val="N"/>
              <AllowLocate val="Y"/>
              <AllowRange val="Y"/>
              <AllowIndexChange val="Y"/>
              <AllowSorting val="Y"/>
              <AllowIOFiles val="Y"/>
              <RecordCycle val="N"/>
              <AllowEvents val="N"/>
              <AllowIndexOptimization val="Y"/>
              <AllowLocationInQuery val="Y"/>
              <AllowPrintingData val="N"/>
            </SIDE_WIN>
            <WIN>
              <OpenTaskWindow val="N"/>
              <CloseTaskWindow val="N"/>
              <ForegroundWindow val="N"/>
              <FlipFld val="N"/>
              <RefreshTaskWindow ReturnValue="N"/>
            </WIN>
            <BOX>
              <Right val="312"/>
              <Bottom val="160"/>
              <Direction val="V"/>
            </BOX>
          </Information>
          <TaskLogic>
            <LogicUnit id="2" propagate="78">
              <Level val="R"/>
              <Type val="M"/>
              <Scope val="S"/>
              <EngineDirective val="S"/>
              <ShowMessage val="Y"/>
              <Condition val="89"/>
              <Event>
                <EventType val="S"/>
                <PublicObject comp="-1"/>
              </Event>
              <Expanded val="1"/>
              <LogicLines>
                <LogicLine>
                  <DATAVIEW_SRC FlowIsn="2" Type="M">
                    <Condition val="N"/>
                    <Modifier val="B"/>
                    <Direction val="C"/>
                  </DATAVIEW_SRC>
                </LogicLine>
                <LogicLine>
                  <LNK Direction="A" EVL_CND="R" FlowIsn="3" Key="5" Mode="R" SortType="6" VIEW="1" VIEWS="2">
                    <DB comp="-1" obj="4"/>
                    <Expanded val="1"/>
                    <Condition val="Y"/>
                  </LNK>
                </LogicLine>
                <LogicLine>
                  <Select FieldID="1" FlowIsn="4" id="1">
                    <Column val="5"/>
                    <Type val="R"/>
                    <IsParameter val="N"/>
                    <Locate MAX="1" MIN="1"/>
                    <DIFF_UPDATE val="T"/>
                    <Condition val="Y"/>
                    <Modifier val="S"/>
                    <Direction val="C"/>
                  </Select>
                </LogicLine>
                <LogicLine>
                  <Select FieldID="2" FlowIsn="5" id="2">
                    <Column val="2"/>
                    <Type val="R"/>
                    <IsParameter val="N"/>
                    <DIFF_UPDATE val="T"/>
                    <Condition val="Y"/>
                    <Modifier val="S"/>
                    <Direction val="C"/>
                  </Select>
                </LogicLine>
                <LogicLine>
                  <END_LINK FlowIsn="6"/>
                </LogicLine>
                <LogicLine>
                  <Remark FlowIsn="7">
                    <Type val="0"/>
                    <Text val=" "/>
                  </Remark>
                </LogicLine>
                <LogicLine>
                  <Select FieldID="3" FlowIsn="8" id="3">
                    <Column val="1"/>
                    <Type val="V"/>
                    <IsParameter val="N"/>
                    <DIFF_UPDATE val="T"/>
                    <Condition val="Y"/>
                    <Modifier val="S"/>
                    <Direction val="C"/>
                  </Select>
                </LogicLine>
                <LogicLine>
                  <LNK Direction="A" EVL_CND="R" FieldID="3" FlowIsn="9" Key="1" Mode="R" SortType="11" VIEW="4" VIEWS="1">
                    <DB comp="-1" obj="4"/>
                    <Expanded val="1"/>
                    <Condition val="Y"/>
                  </LNK>
                </LogicLine>
                <LogicLine>
                  <Select FieldID="4" FlowIsn="10" id="4">
                    <Column val="2"/>
                    <Type val="R"/>
                    <IsParameter val="N"/>
                    <Locate MAX="2" MIN="2"/>
                    <DIFF_UPDATE val="T"/>
                    <Condition val="Y"/>
                    <Modifier val="S"/>
                    <Direction val="C"/>
                  </Select>
                </LogicLine>
                <LogicLine>
                  <END_LINK FlowIsn="11"/>
                </LogicLine>
              </LogicLines>
            </LogicUnit>
            <LogicUnit id="3" propagate="78">
              <Level val="T"/>
              <Type val="P"/>
              <Scope val="S"/>
              <EngineDirective val="S"/>
              <ShowMessage val="Y"/>
              <Condition val="89"/>
              <Event>
                <EventType val="S"/>
                <PublicObject comp="-1"/>
              </Event>
              <Expanded val="1"/>
            </LogicUnit>
            <LogicUnit id="4" propagate="78">
              <Level val="T"/>
              <Type val="S"/>
              <Scope val="S"/>
              <EngineDirective val="S"/>
              <ShowMessage val="Y"/>
              <Condition val="89"/>
              <Event>
                <EventType val="S"/>
                <PublicObject comp="-1"/>
              </Event>
              <Expanded val="1"/>
            </LogicUnit>
            <LogicUnit id="5" propagate="78">
              <Level val="R"/>
              <Type val="P"/>
              <Scope val="S"/>
              <EngineDirective val="S"/>
              <ShowMessage val="Y"/>
              <Condition val="89"/>
              <Event>
                <EventType val="S"/>
                <PublicObject comp="-1"/>
              </Event>
              <Expanded val="1"/>
            </LogicUnit>
            <LogicUnit id="6" propagate="78">
              <Level val="R"/>
              <Type val="S"/>
              <Scope val="S"/>
              <EngineDirective val="S"/>
              <ShowMessage val="Y"/>
              <Condition val="89"/>
              <Event>
                <EventType val="S"/>
                <PublicObject comp="-1"/>
              </Event>
              <Expanded val="1"/>
              <LogicLines>
                <LogicLine>
                  <Remark FlowIsn="12">
                    <Type val="2"/>
                    <Text val=" "/>
                  </Remark>
                </LogicLine>
                <LogicLine>
                  <Update FlowIsn="13">
                    <Parent val="1"/>
                    <FieldID val="13"/>
                    <WithValue val="3"/>
                    <Incremental val="N"/>
                    <ForcedUpdate val="Y"/>
                    <Condition val="Y"/>
                    <Modifier val="B"/>
                    <Direction val="C"/>
                  </Update>
                </LogicLine>
                <LogicLine>
                  <Update FlowIsn="14">
                    <Parent val="1"/>
                    <FieldID val="14"/>
                    <WithValue val="4"/>
                    <Incremental val="N"/>
                    <ForcedUpdate val="Y"/>
                    <Condition val="Y"/>
                    <Modifier val="B"/>
                    <Direction val="C"/>
                  </Update>
                </LogicLine>
                <LogicLine>
                  <Update FlowIsn="15">
                    <Parent val="1"/>
                    <FieldID val="15"/>
                    <WithValue val="5"/>
                    <Incremental val="N"/>
                    <ForcedUpdate val="Y"/>
                    <Condition val="Y"/>
                    <Modifier val="B"/>
                    <Direction val="C"/>
                  </Update>
                </LogicLine>
              </LogicLines>
            </LogicUnit>
          </TaskLogic>
          <TaskForms>
            <FormEntry id="1">
              <PropertyList model="FORM_GUI0">
                <Width id="23" val="366"/>
                <Height id="24" val="231"/>
                <GridX id="38" val="5"/>
                <GridY id="39" val="9"/>
                <Font id="50" val="121"/>
                <Color id="51" val="101"/>
                <_Comment id="218"/>
                <FormName id="311" valUnicode="値取得(pvsw)"/>
                <_TabbingOrder id="318" val="1"/>
                <WindowType id="358" val="1"/>
                <PersistentFormState id="493"/>
              </PropertyList>
            </FormEntry>
          </TaskForms>
          <Expressions>
            <Expression id="1">
              <ExpSyntax val="{1,1}"/>
              <ExpAttribute val="A"/>
            </Expression>
            <Expression id="2">
              <ExpSyntax val="Val (Left (Trim ({1,1}),Len (Trim ({1,1}))-{32768,170}),'10P0Z')*10^{32768,170}"/>
              <ExpAttribute val="N"/>
            </Expression>
            <Expression id="3">
              <ExpSyntax val="{0,2}"/>
              <ExpAttribute val="N"/>
            </Expression>
            <Expression id="4">
              <ExpSyntax val="{0,3}"/>
              <ExpAttribute val="B"/>
            </Expression>
            <Expression id="5">
              <ExpSyntax val="{0,4}"/>
              <ExpAttribute val="N"/>
            </Expression>
          </Expressions>
          <EVNT DESC="Levt_８桁バースキャン" FORCE_EXIT="N" id="1">
            <Event>
              <EventType val="N"/>
              <PublicObject comp="-1"/>
            </Event>
          </EVNT>
          <EVNT DESC="Levt_エージェント用" FORCE_EXIT="N" id="2">
            <Event>
              <EventType val="N"/>
              <PublicObject comp="-1"/>
            </Event>
          </EVNT>
        </Task>
        <Task MainProgram="N">
          <Header Description="値取得(msdeCommon)" ISN_2="3" id="372">
            <ExecutionRight comp="-1"/>
            <Resident val="N"/>
            <SQL val="N"/>
            <ReturnValue>
              <ReturnValueAttr/>
              <ParametersAttributes/>
            </ReturnValue>
            <SqlWhereExist val="N"/>
            <TaskType val="B"/>
            <External val="N"/>
            <FormType val="N"/>
            <DotNetObjectExists val="N"/>
            <LastModified _date="733855" _time="64106" date="2010/03/24" time="17:48:26"/>
          </Header>
          <ItemIsn val="4"/>
          <Resource>
            <DB id="1">
              <DataObject comp="-1" obj="689"/>
              <Access val="R"/>
              <Share val="W"/>
              <Open val="N"/>
              <Cache val="N"/>
              <IdentifyRowModifications val="84"/>
            </DB>
            <Columns>
              <Column id="1" name="M.エージェント会社">
                <PropertyList model="FIELD">
                  <Model attr_obj="FIELD_LOGICAL" id="1"/>
                  <GuiDisplay id="158">
                    <PropertyList model="CTRL_GUI0_EDIT">
                      <Font id="50" val="101"/>
                      <Color id="51" val="101"/>
                      <V11Style id="539" val="4"/>
                    </PropertyList>
                  </GuiDisplay>
                  <GuiDisplayTable id="159">
                    <PropertyList model="CTRL_GUI0_EDIT">
                      <Font id="50" val="101"/>
                      <Color id="51" val="101"/>
                    </PropertyList>
                  </GuiDisplayTable>
                  <GuiOutput id="160">
                    <PropertyList model="CTRL_GUI1_EDIT">
                      <Font id="50" val="101"/>
                      <Color id="51" val="101"/>
                    </PropertyList>
                  </GuiOutput>
                  <GuiOutputTable id="161">
                    <PropertyList model="CTRL_GUI1_EDIT">
                      <Font id="50" val="101"/>
                      <Color id="51" val="101"/>
                    </PropertyList>
                  </GuiOutputTable>
                  <NullValue id="167"/>
                  <StoredAs id="173" val="1"/>
                  <Definition id="175" val="2"/>
                </PropertyList>
              </Column>
            </Columns>
          </Resource>
          <Information>
            <Key>
              <Mode val="N"/>
            </Key>
            <DB comp="-1"/>
            <Sort>
              <CLS val="A"/>
            </Sort>
            <ForceRecordDelete DEL="N"/>
            <EndTaskCondition val="Y"/>
            <EvaluateEndCondition val="A"/>
            <InitialMode val="M"/>
            <Locate Direction="A"/>
            <Range Direction="A"/>
            <VarRange/>
            <TaskProperties>
              <SelectionTable val="N"/>
              <ConfirmUpdate CNFU="N"/>
              <ConfirmCancel val="N"/>
              <ErrorStrategy val="A"/>
              <LockingStrategy val="I"/>
              <CacheStrategy val="N"/>
              <ForceRecordSuffix val="N"/>
              <TransactionMode val="P"/>
              <TransactionBegin val="T"/>
              <PreloadView val="N"/>
              <AllowEmptyDataview val="N"/>
              <KeepCreatedContext val="N"/>
            </TaskProperties>
            <SIDE_WIN>
              <AllowOptions val="N"/>
              <AllowQuery val="Y"/>
              <AllowModify val="Y"/>
              <AllowCreate val="Y"/>
              <AllowDelete val="N"/>
              <AllowLocate val="Y"/>
              <AllowRange val="Y"/>
              <AllowIndexChange val="Y"/>
              <AllowSorting val="Y"/>
              <AllowIOFiles val="Y"/>
              <RecordCycle val="N"/>
              <AllowEvents val="N"/>
              <AllowIndexOptimization val="Y"/>
              <AllowLocationInQuery val="Y"/>
              <AllowPrintingData val="N"/>
            </SIDE_WIN>
            <WIN>
              <OpenTaskWindow val="N"/>
              <CloseTaskWindow val="N"/>
              <ForegroundWindow val="N"/>
              <FlipFld val="N"/>
              <RefreshTaskWindow ReturnValue="N"/>
            </WIN>
            <BOX>
              <Right val="312"/>
              <Bottom val="160"/>
              <Direction val="V"/>
            </BOX>
          </Information>
          <TaskLogic>
            <LogicUnit id="2" propagate="78">
              <Level val="R"/>
              <Type val="M"/>
              <Scope val="S"/>
              <EngineDirective val="S"/>
              <ShowMessage val="Y"/>
              <Condition val="89"/>
              <Event>
                <EventType val="S"/>
                <PublicObject comp="-1"/>
              </Event>
              <Expanded val="1"/>
              <LogicLines>
                <LogicLine>
                  <DATAVIEW_SRC FlowIsn="2" Type="M">
                    <Condition val="N"/>
                    <Modifier val="B"/>
                    <Direction val="C"/>
                  </DATAVIEW_SRC>
                </LogicLine>
                <LogicLine>
                  <LNK Direction="A" EVL_CND="R" FlowIsn="3" Key="5" Mode="R" SortType="6" VIEW="1" VIEWS="2">
                    <DB comp="-1" obj="689"/>
                    <Expanded val="1"/>
                    <Condition val="Y"/>
                  </LNK>
                </LogicLine>
                <LogicLine>
                  <Select FieldID="1" FlowIsn="4" id="1">
                    <Column val="5"/>
                    <Type val="R"/>
                    <IsParameter val="N"/>
                    <Locate MAX="1" MIN="1"/>
                    <DIFF_UPDATE val="T"/>
                    <Condition val="Y"/>
                    <Modifier val="S"/>
                    <Direction val="C"/>
                  </Select>
                </LogicLine>
                <LogicLine>
                  <Select FieldID="2" FlowIsn="5" id="2">
                    <Column val="2"/>
                    <Type val="R"/>
                    <IsParameter val="N"/>
                    <DIFF_UPDATE val="T"/>
                    <Condition val="Y"/>
                    <Modifier val="S"/>
                    <Direction val="C"/>
                  </Select>
                </LogicLine>
                <LogicLine>
                  <END_LINK FlowIsn="6"/>
                </LogicLine>
                <LogicLine>
                  <Remark FlowIsn="7">
                    <Type val="0"/>
                    <Text val=" "/>
                  </Remark>
                </LogicLine>
                <LogicLine>
                  <Select FieldID="3" FlowIsn="8" id="3">
                    <Column val="1"/>
                    <Type val="V"/>
                    <IsParameter val="N"/>
                    <DIFF_UPDATE val="T"/>
                    <Condition val="Y"/>
                    <Modifier val="S"/>
                    <Direction val="C"/>
                  </Select>
                </LogicLine>
                <LogicLine>
                  <LNK Direction="A" EVL_CND="R" FieldID="3" FlowIsn="9" Key="1" Mode="R" SortType="11" VIEW="4" VIEWS="1">
                    <DB comp="-1" obj="689"/>
                    <Expanded val="1"/>
                    <Condition val="Y"/>
                  </LNK>
                </LogicLine>
                <LogicLine>
                  <Select FieldID="4" FlowIsn="10" id="4">
                    <Column val="2"/>
                    <Type val="R"/>
                    <IsParameter val="N"/>
                    <Locate MAX="2" MIN="2"/>
                    <DIFF_UPDATE val="T"/>
                    <Condition val="Y"/>
                    <Modifier val="S"/>
                    <Direction val="C"/>
                  </Select>
                </LogicLine>
                <LogicLine>
                  <END_LINK FlowIsn="11"/>
                </LogicLine>
              </LogicLines>
            </LogicUnit>
            <LogicUnit id="3" propagate="78">
              <Level val="T"/>
              <Type val="P"/>
              <Scope val="S"/>
              <EngineDirective val="S"/>
              <ShowMessage val="Y"/>
              <Condition val="89"/>
              <Event>
                <EventType val="S"/>
                <PublicObject comp="-1"/>
              </Event>
              <Expanded val="1"/>
            </LogicUnit>
            <LogicUnit id="4" propagate="78">
              <Level val="T"/>
              <Type val="S"/>
              <Scope val="S"/>
              <EngineDirective val="S"/>
              <ShowMessage val="Y"/>
              <Condition val="89"/>
              <Event>
                <EventType val="S"/>
                <PublicObject comp="-1"/>
              </Event>
              <Expanded val="1"/>
            </LogicUnit>
            <LogicUnit id="5" propagate="78">
              <Level val="R"/>
              <Type val="P"/>
              <Scope val="S"/>
              <EngineDirective val="S"/>
              <ShowMessage val="Y"/>
              <Condition val="89"/>
              <Event>
                <EventType val="S"/>
                <PublicObject comp="-1"/>
              </Event>
              <Expanded val="1"/>
            </LogicUnit>
            <LogicUnit id="6" propagate="78">
              <Level val="R"/>
              <Type val="S"/>
              <Scope val="S"/>
              <EngineDirective val="S"/>
              <ShowMessage val="Y"/>
              <Condition val="89"/>
              <Event>
                <EventType val="S"/>
                <PublicObject comp="-1"/>
              </Event>
              <Expanded val="1"/>
              <LogicLines>
                <LogicLine>
                  <Remark FlowIsn="12">
                    <Type val="2"/>
                    <Text val=" "/>
                  </Remark>
                </LogicLine>
                <LogicLine>
                  <Update FlowIsn="13">
                    <Parent val="1"/>
                    <FieldID val="13"/>
                    <WithValue val="3"/>
                    <Incremental val="N"/>
                    <ForcedUpdate val="Y"/>
                    <Condition val="Y"/>
                    <Modifier val="B"/>
                    <Direction val="C"/>
                  </Update>
                </LogicLine>
                <LogicLine>
                  <Update FlowIsn="14">
                    <Parent val="1"/>
                    <FieldID val="14"/>
                    <WithValue val="4"/>
                    <Incremental val="N"/>
                    <ForcedUpdate val="Y"/>
                    <Condition val="Y"/>
                    <Modifier val="B"/>
                    <Direction val="C"/>
                  </Update>
                </LogicLine>
                <LogicLine>
                  <Update FlowIsn="15">
                    <Parent val="1"/>
                    <FieldID val="15"/>
                    <WithValue val="5"/>
                    <Incremental val="N"/>
                    <ForcedUpdate val="Y"/>
                    <Condition val="Y"/>
                    <Modifier val="B"/>
                    <Direction val="C"/>
                  </Update>
                </LogicLine>
              </LogicLines>
            </LogicUnit>
          </TaskLogic>
          <TaskForms>
            <FormEntry id="1">
              <PropertyList model="FORM_GUI0">
                <Width id="23" val="366"/>
                <Height id="24" val="231"/>
                <GridX id="38" val="5"/>
                <GridY id="39" val="9"/>
                <Font id="50" val="121"/>
                <Color id="51" val="101"/>
                <_Comment id="218"/>
                <FormName id="311" valUnicode="値取得(msdeCommon)"/>
                <_TabbingOrder id="318" val="1"/>
                <WindowType id="358" val="1"/>
                <PersistentFormState id="493"/>
              </PropertyList>
            </FormEntry>
          </TaskForms>
          <Expressions>
            <Expression id="1">
              <ExpSyntax val="{1,1}"/>
              <ExpAttribute val="A"/>
            </Expression>
            <Expression id="2">
              <ExpSyntax val="Val (Left (Trim ({1,1}),Len (Trim ({1,1}))-{32768,170}),'10P0Z')*10^{32768,170}"/>
              <ExpAttribute val="N"/>
            </Expression>
            <Expression id="3">
              <ExpSyntax val="{0,2}"/>
              <ExpAttribute val="N"/>
            </Expression>
            <Expression id="4">
              <ExpSyntax val="{0,3}"/>
              <ExpAttribute val="B"/>
            </Expression>
            <Expression id="5">
              <ExpSyntax val="{0,4}"/>
              <ExpAttribute val="N"/>
            </Expression>
          </Expressions>
          <EVNT DESC="Levt_８桁バースキャン" FORCE_EXIT="N" id="1">
            <Event>
              <EventType val="N"/>
              <PublicObject comp="-1"/>
            </Event>
          </EVNT>
          <EVNT DESC="Levt_エージェント用" FORCE_EXIT="N" id="2">
            <Event>
              <EventType val="N"/>
              <PublicObject comp="-1"/>
            </Event>
          </EVNT>
        </Task>
      </Task>
    </Programs>
  </ProgramsRepository>

</Application>
